st_chat_input_multimodal/__init__.py
st_chat_input_multimodal/frontend/build/bootstrap.min.css
st_chat_input_multimodal/frontend/build/index.html
st_chat_input_multimodal/frontend/build/assets/index-BQ4QkGRG.js
st_chat_input_multimodal-1.0.6.dist-info/licenses/LICENSE
st_chat_input_multimodal-1.0.6.dist-info/METADATA
st_chat_input_multimodal-1.0.6.dist-info/WHEEL
st_chat_input_multimodal-1.0.6.dist-info/top_level.txt
st_chat_input_multimodal-1.0.6.dist-info/RECORD
